{
  "parent": "minecraft:recipes/root",
  "criteria": {
    "has_slime_like_goo": {
      "conditions": {
        "items": [
          {
            "items": [
              "frogvasion:slime_like_goo"
            ]
          }
        ]
      },
      "trigger": "minecraft:inventory_changed"
    },
    "has_the_recipe": {
      "conditions": {
        "recipe": "frogvasion:rubber"
      },
      "trigger": "minecraft:recipe_unlocked"
    }
  },
  "requirements": [
    [
      "has_slime_like_goo",
      "has_the_recipe"
    ]
  ],
  "rewards": {
    "recipes": [
      "frogvasion:rubber"
    ]
  },
  "sends_telemetry_event": false
}